pre_processing_text_basic_tools/__init__.py
pre_processing_text_basic_tools/main.py
pre_processing_text_basic_tools-0.5.dist-info/METADATA
pre_processing_text_basic_tools-0.5.dist-info/WHEEL
pre_processing_text_basic_tools-0.5.dist-info/top_level.txt
pre_processing_text_basic_tools-0.5.dist-info/RECORD
