Metadata-Version: 2.1
Name: pre_processing_text_basic_tools
Version: 0.5
Summary: Toolkit for basic steps on Natural Language Processing - aimed on portuguese BR language.
Author: Igor Caetano de Souza
Project-URL: GitHub Repository, https://github.com/IgorCaetano/pre_processing_text_basic_tools
Requires-Dist: regex
